{"314":{"name":"Stanton","danger":10},"315":{"name":"Nyx","danger":0},"316":{"name":"Terra","danger":0},"317":{"name":"Virgil","danger":0},"318":{"name":"Pyro","danger":0},"319":{"name":"Magnus","danger":0},"320":{"name":"Nul","danger":0},"321":{"name":"Taranis","danger":0},"322":{"name":"Vega","danger":0},"323":{"name":"Ellis","danger":0},"324":{"name":"Odin","danger":0},"325":{"name":"Helios","danger":0},"326":{"name":"Kellog","danger":0},"327":{"name":"Tiber","danger":0},"328":{"name":"Osiris","danger":0},"329":{"name":"Fora","danger":0},"331":{"name":"Bremen","danger":0},"332":{"name":"Oso","danger":0},"333":{"name":"Tayac","danger":0},"334":{"name":"Chronos","danger":0},"335":{"name":"Min","danger":0},"336":{"name":"Kallis","danger":0},"337":{"name":"Castra","danger":0},"338":{"name":"Hades","danger":0},"339":{"name":"Caliban","danger":0},"340":{"name":"Davien","danger":0},"342":{"name":"Baker","danger":0},"344":{"name":"Kilian","danger":0},"346":{"name":"Banshee","danger":0},"347":{"name":"Tyrol","danger":0},"348":{"name":"Oberon","danger":0},"349":{"name":"Rhetor","danger":0},"355":{"name":"Sol","danger":0},"356":{"name":"Goss","danger":0},"357":{"name":"Nexus","danger":0},"360":{"name":"Orion","danger":0},"361":{"name":"Nemo","danger":0},"362":{"name":"Centauri","danger":0},"363":{"name":"Elysium","danger":0},"364":{"name":"Idris","danger":0},"367":{"name":"Ferron","danger":0},"369":{"name":"Croshaw","danger":0},"370":{"name":"Corel","danger":0},"372":{"name":"Cathcart","danger":0},"376":{"name":"Virtus","danger":0},"377":{"name":"Hadur","danger":0},"378":{"name":"Virgo","danger":0},"379":{"name":"Viking","danger":0},"380":{"name":"Volt","danger":0},"381":{"name":"Kins","danger":0},"382":{"name":"Kayfa","danger":0},"383":{"name":"Vulture","danger":0},"384":{"name":"Bacchus","danger":0},"385":{"name":"Tal","danger":0},"386":{"name":"Gliese","danger":0},"387":{"name":"Vesper","danger":0},"388":{"name":"Eealus","danger":0},"389":{"name":"Khabari","danger":0},"390":{"name":"Geddon","danger":0},"391":{"name":"Vanguard","danger":0},"392":{"name":"Veritas","danger":0},"394":{"name":"Vagabond","danger":0},"395":{"name":"Markahil","danger":0},"396":{"name":"El'sin","danger":0},"397":{"name":"Pallas","danger":0},"398":{"name":"Ayr'ka","danger":0},"399":{"name":"Indra","danger":0},"400":{"name":"Trise","danger":0},"401":{"name":"Rihlah","danger":0},"402":{"name":"Yulin","danger":0},"403":{"name":"Voodoo","danger":0},"404":{"name":"Vermilion","danger":0},"405":{"name":"Vendetta","danger":0},"406":{"name":"Vector","danger":0},"407":{"name":"Charon","danger":0},"408":{"name":"Gurzil","danger":0},"409":{"name":"Oya","danger":0},"410":{"name":"Leir","danger":0},"411":{"name":"Hadrian","danger":0},"412":{"name":"Garron","danger":0},"413":{"name":"Horus","danger":0},"414":{"name":"Genesis","danger":0},"415":{"name":"Kiel","danger":0},"416":{"name":"Branaugh","danger":0},"417":{"name":"Tohil","danger":0},"418":{"name":"Cano","danger":0},"419":{"name":"Kabal","danger":0},"420":{"name":"Tanga","danger":0},"421":{"name":"Oretani","danger":0},"422":{"name":"Tamsa","danger":0}}